Metadata-Version: 2.1
Name: double-pendula
Version: 0.1.4
Summary: Library for animating double pendula in Python
Home-page: https://github.com/chris-greening/double-pendula
Author: Chris Greening
Author-email: chris@christophergreening.com
License: UNKNOWN
Platform: UNKNOWN
Classifier: Programming Language :: Python :: 3
Classifier: License :: OSI Approved :: MIT License
Classifier: Operating System :: OS Independent
Requires-Python: >=3.7
License-File: LICENSE
